hogwarts_android_mcp-0.1.3-py3-none-any.whl
hogwarts_android_mcp/__init__.py
hogwarts_android_mcp/__main__.py
hogwarts_android_mcp/model/__init__.py
hogwarts_android_mcp/model/adb_model.py
hogwarts_android_mcp/model/settings.py
hogwarts_android_mcp/model/xml_filter_model.py
hogwarts_android_mcp/pyarmor_runtime_000000/__init__.py
hogwarts_android_mcp/pyarmor_runtime_000000/darwin_universal/pyarmor_runtime.so
hogwarts_android_mcp/pyarmor_runtime_000000/linux_aarch64/pyarmor_runtime.so
hogwarts_android_mcp/pyarmor_runtime_000000/linux_x86_64/pyarmor_runtime.so
hogwarts_android_mcp/pyarmor_runtime_000000/windows_x86_64/pyarmor_runtime.pyd
hogwarts_android_mcp/service/__init__.py
hogwarts_android_mcp/service/adb_service.py
hogwarts_android_mcp/service/android_mcp.py
hogwarts_android_mcp/service/xml_service.py
hogwarts_android_mcp/tests/__init__.py
hogwarts_android_mcp/tests/test_adb_service.py
hogwarts_android_mcp/tests/test_xml_service.py
hogwarts_android_mcp/util/__init__.py
hogwarts_android_mcp/util/log.py
hogwarts_android_mcp-0.1.3.dist-info/METADATA
hogwarts_android_mcp-0.1.3.dist-info/RECORD.bak
hogwarts_android_mcp-0.1.3.dist-info/WHEEL
hogwarts_android_mcp-0.1.3.dist-info/entry_points.txt
hogwarts_android_mcp-0.1.3.dist-info/top_level.txt
hogwarts_android_mcp-0.1.3.dist-info/RECORD
