Metadata-Version: 2.4
Name: hogwarts-android-mcp
Version: 0.1.3
Summary: android adb mcp tool
Requires-Python: >=3.10
Requires-Dist: beautifulsoup4>=4.14.2
Requires-Dist: hogwarts-mcp>=0.1.0
Requires-Dist: lxml>=6.0.2
Requires-Dist: pydantic>=2.12.2
Requires-Dist: pytest>=8.4.2
